{"cameraMode":{"drawMode":0,"name":"Shaded","section":"Shading Mode"},"sceneLighting":false,"audioPlay":false,"sceneViewState":{"m_AlwaysRefresh":false,"showFog":true,"showSkybox":false,"showFlares":true,"showImageEffects":true,"showParticleSystems":true,"showVisualEffectGraphs":true,"m_FxEnabled":true},"in2DMode":false,"pivot":{"x":5.039999961853027,"y":2.940000057220459,"z":-89.11000061035156},"rotation":{"x":0.07130976021289826,"y":-0.9256371259689331,"z":0.3000663220882416,"w":0.21972475945949555},"size":0.8660253882408142,"orthographic":false}